llm_clap.py
llm_clap-0.2.dist-info/LICENSE
llm_clap-0.2.dist-info/METADATA
llm_clap-0.2.dist-info/WHEEL
llm_clap-0.2.dist-info/entry_points.txt
llm_clap-0.2.dist-info/top_level.txt
llm_clap-0.2.dist-info/RECORD
