Metadata-Version: 2.1
Name: llm-clap
Version: 0.2
Summary: Generate embeddings for audio files using CLAP with llm
Author: Evangelos Lamprou
License: Apache-2.0
Project-URL: Homepage, https://github.com/vagos/llm-clap
Project-URL: Changelog, https://github.com/vagos/llm-clap/releases
Project-URL: Issues, https://github.com/vagos/llm-clap/issues
Classifier: License :: OSI Approved :: Apache Software License
License-File: LICENSE
Requires-Dist: llm >=0.10
Requires-Dist: transformers
Requires-Dist: torch
Requires-Dist: torchaudio
Requires-Dist: librosa
Provides-Extra: test
Requires-Dist: pytest ; extra == 'test'
